vrint/__init__.py
vrint/vrint.py
vrint-0.2.2.dist-info/METADATA
vrint-0.2.2.dist-info/WHEEL
vrint-0.2.2.dist-info/top_level.txt
vrint-0.2.2.dist-info/RECORD
