Metadata-Version: 2.4
Name: vrint
Version: 0.2.2
Summary: A package that provides a verbose print function
Author-email: Huayra1 <Huayra1@live.no>
License: MIT License
Project-URL: Homepage, https://github.com/Huayra1/vrint
Project-URL: Bug Tracker, https://github.com/Huayra1/vrint/issues
Project-URL: Documentation, https://github.com/Huayra1/vrint/blob/main/README.md
Project-URL: Source Code, https://github.com/Huayra1/vrint
Project-URL: Changelog, https://github.com/Huayra1/vrint/blob/main/CHANGELOG.md
Project-URL: License, https://github.com/Huayra1/vrint/blob/main/LICENSE
Project-URL: Releases, https://github.com/Huayra1/vrint/releases
Project-URL: Issues, https://github.com/Huayra1/vrint/issues
Requires-Python: >=3.6
